LICENSE
MANIFEST.in
README.md
setup.cfg
setup.py
indico_payment_razorpay/__init__.py
indico_payment_razorpay/blueprint.py
indico_payment_razorpay/controllers.py
indico_payment_razorpay/forms.py
indico_payment_razorpay/plugin.py
indico_payment_razorpay/util.py
indico_payment_razorpay/templates/checkout.html
indico_payment_razorpay/templates/event_payment_form.html
indico_payment_razorpay/templates/transaction_details.html
indico_plugin_payment_razorpay.egg-info/PKG-INFO
indico_plugin_payment_razorpay.egg-info/SOURCES.txt
indico_plugin_payment_razorpay.egg-info/dependency_links.txt
indico_plugin_payment_razorpay.egg-info/entry_points.txt
indico_plugin_payment_razorpay.egg-info/not-zip-safe
indico_plugin_payment_razorpay.egg-info/requires.txt
indico_plugin_payment_razorpay.egg-info/top_level.txt