Metadata-Version: 2.1
Name: indico-plugin-payment-razorpay
Version: 3.0.5.1
Summary: Razorpay payments for Indico event registration fees
Home-page: https://github.com/adityamj/indico-payment-razorpay
Author: Aditya Jain
Author-email: aj@adityaj.in
License: MIT
Platform: UNKNOWN
Classifier: Environment :: Plugins
Classifier: Environment :: Web Environment
Classifier: License :: OSI Approved :: MIT License
Classifier: Programming Language :: Python :: 3.9
Requires-Python: ~=3.9.0
License-File: LICENSE
